zippy_ip_scanner-1.1.0.data/data/share/applications/ZippyIpScanner.desktop
zippy_ip_scanner-1.1.0.data/data/share/zippyipscanner/zippyipscanner.ico
zippy_ip_scanner-1.1.0.dist-info/DESCRIPTION.rst
zippy_ip_scanner-1.1.0.dist-info/METADATA
zippy_ip_scanner-1.1.0.dist-info/RECORD
zippy_ip_scanner-1.1.0.dist-info/WHEEL
zippy_ip_scanner-1.1.0.dist-info/entry_points.txt
zippy_ip_scanner-1.1.0.dist-info/metadata.json
zippy_ip_scanner-1.1.0.dist-info/top_level.txt
zippyipscanner/__init__.py
zippyipscanner/about.py
zippyipscanner/functions.py
zippyipscanner/license.py
zippyipscanner/mathfunctions.py
zippyipscanner/portable.py
zippyipscanner/splash.png
zippyipscanner/version.py
zippyipscanner/zippyipscanner.ico
zippyipscanner/zippyipscanner.py
zippyipscanner/base/__init__.py
zippyipscanner/base/filteredmodel.py
zippyipscanner/dialogs/__init__.py
zippyipscanner/dialogs/checkforupdates.py
zippyipscanner/dialogs/settings.py
zippyipscanner/forms/__init__.py
zippyipscanner/forms/mainwindow.py
zippyipscanner/forms/uiaboutdialog.py
zippyipscanner/forms/uicheckforupdates.py
zippyipscanner/forms/uimainwindow.py
zippyipscanner/forms/uisettingsdialog.py
zippyipscanner/forms/uisubmitissuedialog.py
zippyipscanner/images/clear.png
zippyipscanner/images/start.png
zippyipscanner/images/stop.png
